[
  {
    "subject_type": 1, 
    "visit_notify": false, 
    "create_time": 1540504897, 
    "job_number": "0", 
    "title": "", 
    "company_id": 1, 
    "id": 1, 
    "entry_date": null, 
    "department": "", 
    "email": "", 
    "avatar": "2018-10-26/v2_de9e7c54fbe59cb871e6fbfd0e07dd6c0b93e710.jpg", 
    "password_reseted": false, 
    "description": "\u6211\u5f88\u5e05", 
    "pinyin": "chenzenghua", 
    "start_time": 1540392900, 
    "interviewee": "", 
    "phone": "", 
    "birthday": null, 
    "purpose": 0, 
    "come_from": "\u4e0a\u6d77\u5e06\u4e00\u5c1a\u884c\u79d1\u6280\u6709\u9650\u516c\u53f8", 
    "remark": "\u6211\u975e\u5e38\u5e05", 
    "name": "\u9648\u589e\u534e", 
    "photos": [
      "2018-10-26/v2_25e43e8a1fb5157f5622f9d696b6096659c137b7.jpg", 
      "2018-10-26/v2_92524c2b999b857050b61325b2f3b521d3b73698.jpg", 
      "2018-10-26/v2_6dfaeb013af1215ee0b8bf7c7cf17480438d2ecb.jpg"
    ], 
    "gender": 0, 
    "end_time": 1543589700, 
    "interviewee_pinyin": ""
  }, 
  {
    "subject_type": 1, 
    "visit_notify": false, 
    "create_time": 1541578551, 
    "job_number": "0", 
    "title": "", 
    "company_id": 1, 
    "id": 61, 
    "entry_date": null, 
    "department": "", 
    "email": "", 
    "avatar": "2018-11-07/v2_84776b0b76613763cbc707d51c757fc810d73942.jpg", 
    "password_reseted": false, 
    "description": "", 
    "pinyin": "fengyingrui", 
    "start_time": 1541434440, 
    "interviewee": "\u8c2d\u9ece\u660e", 
    "phone": "", 
    "birthday": null, 
    "purpose": 0, 
    "come_from": "Thoughtworks", 
    "remark": "", 
    "name": "\u51af\u82f1\u777f", 
    "photos": [
      "2018-11-07/v2_d5dc8857d352630b86f75901a674bb9f4a74c724.png"
    ], 
    "gender": 0, 
    "end_time": 1548924720, 
    "interviewee_pinyin": "tanliming"
  }, 
  {
    "subject_type": 1, 
    "visit_notify": false, 
    "create_time": 1541578617, 
    "job_number": "0", 
    "title": "", 
    "company_id": 1, 
    "id": 62, 
    "entry_date": null, 
    "department": "", 
    "email": "", 
    "avatar": "2018-11-07/v2_f7702e3d69be727e8dd834040c275dc93538de5b.jpg", 
    "password_reseted": false, 
    "description": "", 
    "pinyin": "luoqian", 
    "start_time": 1541520000, 
    "interviewee": "\u8c2d\u9ece\u660e", 
    "phone": "", 
    "birthday": null, 
    "purpose": 0, 
    "come_from": "Thoughtworks", 
    "remark": "", 
    "name": "\u7f57\u5029", 
    "photos": [
      "2018-11-07/v2_11374b524233d521a9c5be2a87e1f27767d33e46.png"
    ], 
    "gender": 0, 
    "end_time": 1556636280, 
    "interviewee_pinyin": "tanliming"
  }, 
  {
    "subject_type": 1, 
    "visit_notify": false, 
    "create_time": 1541578648, 
    "job_number": "0", 
    "title": "", 
    "company_id": 1, 
    "id": 63, 
    "entry_date": null, 
    "department": "", 
    "email": "", 
    "avatar": "2018-11-07/v2_ff4778f965bb80bd4fb6b48a9b0b5b45e6b02119.jpg", 
    "password_reseted": false, 
    "description": "", 
    "pinyin": "zhuzhiguo", 
    "start_time": 1541007420, 
    "interviewee": "\u8c2d\u9ece\u660e", 
    "phone": "", 
    "birthday": null, 
    "purpose": 0, 
    "come_from": "Thoughtworks", 
    "remark": "", 
    "name": "\u6731\u5fd7\u56fd", 
    "photos": [
      "2018-11-07/v2_4440a3e3279123ac7fad1dcfd0158e13ba109c6e.png"
    ], 
    "gender": 0, 
    "end_time": 1542185520, 
    "interviewee_pinyin": ""
  }, 
  {
    "subject_type": 1, 
    "visit_notify": false, 
    "create_time": 1543454677, 
    "job_number": "0", 
    "title": "", 
    "company_id": 1, 
    "id": 68, 
    "entry_date": null, 
    "department": "", 
    "email": "", 
    "avatar": "2018-11-29/v2_38303a8ed4ae7cdb6749f8da1ede33d1621cb195.jpg", 
    "password_reseted": false, 
    "description": "", 
    "pinyin": "tangyun", 
    "start_time": 1543454220, 
    "interviewee": "\u8c2d\u9ece\u660e", 
    "phone": "", 
    "birthday": null, 
    "purpose": 0, 
    "come_from": "", 
    "remark": "", 
    "name": "\u5510\u4e91", 
    "photos": [
      "2018-11-29/v2_5d4876a3ab43ba7b4b4b1140ab7256952bf93c68.jpg"
    ], 
    "gender": 0, 
    "end_time": 1580525700, 
    "interviewee_pinyin": "tanliming"
  }, 
  {
    "subject_type": 1, 
    "visit_notify": false, 
    "create_time": 1546929107, 
    "job_number": "0", 
    "title": "", 
    "company_id": 1, 
    "id": 78, 
    "entry_date": null, 
    "department": "", 
    "email": "", 
    "avatar": "2019-01-08/v2_9890c21dbe7f88b18c0211bc1646b2ace036cf9e.jpg", 
    "password_reseted": false, 
    "description": "\u6b22\u8fce\u5e72\u603b", 
    "pinyin": "ganzhenyu", 
    "start_time": 1546842600, 
    "interviewee": "", 
    "phone": "", 
    "birthday": null, 
    "purpose": 2, 
    "come_from": "\u70e8\u4e91", 
    "remark": "", 
    "name": "\u5e72\u9707\u5b87", 
    "photos": [
      "2019-01-08/v2_4cff7b52758db40c08e6eea558543d332a0753de.jpg"
    ], 
    "gender": 0, 
    "end_time": 1648881000, 
    "interviewee_pinyin": ""
  }, 
  {
    "subject_type": 1, 
    "visit_notify": false, 
    "create_time": 1551760301, 
    "job_number": "0", 
    "title": "", 
    "company_id": 1, 
    "id": 81, 
    "entry_date": null, 
    "department": "", 
    "email": "", 
    "avatar": "2019-03-05/v2_104a26b0a2c78439d81024b6a73a2dd3cdb5aab5.jpg", 
    "password_reseted": false, 
    "description": "", 
    "pinyin": "haolaigongchengshi", 
    "start_time": 1551673800, 
    "interviewee": "\u8c2d\u9ece\u660e", 
    "phone": "", 
    "birthday": null, 
    "purpose": 0, 
    "come_from": "\u660a\u6765", 
    "remark": "", 
    "name": "\u660a\u6765\u5de5\u7a0b\u5e08", 
    "photos": [
      "2019-03-05/v2_e407a5de3a40d8b096f78f5e446a63fb614b064c.jpg"
    ], 
    "gender": 0, 
    "end_time": 1554036960, 
    "interviewee_pinyin": "tanliming"
  }, 
  {
    "subject_type": 1, 
    "visit_notify": false, 
    "create_time": 1556105718, 
    "job_number": "0", 
    "title": "", 
    "company_id": 1, 
    "id": 151, 
    "entry_date": null, 
    "department": "", 
    "email": "", 
    "avatar": "2019-04-24/v2_d7df5b4953ade3dc6607a6d5dda05d57a539d8dd.jpg", 
    "password_reseted": false, 
    "description": "", 
    "pinyin": "zhouyang", 
    "start_time": 1556104380, 
    "interviewee": "\u8c2d\u9ece\u660e", 
    "phone": "", 
    "birthday": null, 
    "purpose": 2, 
    "come_from": "Thoughtworks", 
    "remark": "", 
    "name": "\u5468\u9633", 
    "photos": [
      "2019-04-24/v2_cc82ef8cc666e4e1639103a5916b2606094069a4.jpg"
    ], 
    "gender": 0, 
    "end_time": 1575588840, 
    "interviewee_pinyin": "tanliming"
  }, 
  {
    "subject_type": 1, 
    "visit_notify": false, 
    "create_time": 1556105755, 
    "job_number": "0", 
    "title": "", 
    "company_id": 1, 
    "id": 152, 
    "entry_date": null, 
    "department": "", 
    "email": "", 
    "avatar": "2019-04-24/v2_fdd5dbbc22583f2a3eb1657f42ad6b477f238cd5.jpg", 
    "password_reseted": false, 
    "description": "", 
    "pinyin": "suyue", 
    "start_time": 1556084940, 
    "interviewee": "\u8c2d\u9ece\u660e", 
    "phone": "", 
    "birthday": null, 
    "purpose": 0, 
    "come_from": "", 
    "remark": "", 
    "name": "\u82cf\u8d8a", 
    "photos": [
      "2019-04-24/v2_f895c40e63f7d0443dde29d7ff0f319c4af211b9.jpg"
    ], 
    "gender": 0, 
    "end_time": 1575585720, 
    "interviewee_pinyin": "tanliming"
  }, 
  {
    "subject_type": 1, 
    "visit_notify": false, 
    "create_time": 1556105791, 
    "job_number": "0", 
    "title": "", 
    "company_id": 1, 
    "id": 153, 
    "entry_date": null, 
    "department": "", 
    "email": "", 
    "avatar": "2019-04-24/v2_472fc917a506c1400c17289f5d1a81d6b2eccabd.jpg", 
    "password_reseted": false, 
    "description": "", 
    "pinyin": "zhouzhewu", 
    "start_time": 1556084700, 
    "interviewee": "\u8c2d\u9ece\u660e", 
    "phone": "", 
    "birthday": null, 
    "purpose": 0, 
    "come_from": "", 
    "remark": "", 
    "name": "\u5468\u54f2\u6b66", 
    "photos": [
      "2019-04-24/v2_5672a5ea496789075da1cf67f43b2cbfae818dc7.jpg"
    ], 
    "gender": 0, 
    "end_time": 1570837380, 
    "interviewee_pinyin": "tanliming"
  }, 
  {
    "subject_type": 1, 
    "visit_notify": false, 
    "create_time": 1556105823, 
    "job_number": "0", 
    "title": "", 
    "company_id": 1, 
    "id": 154, 
    "entry_date": null, 
    "department": "", 
    "email": "", 
    "avatar": "2019-04-24/v2_86e6680756a3de9122ed0aa3348db8f766209548.jpg", 
    "password_reseted": false, 
    "description": "", 
    "pinyin": "qinfanpeng", 
    "start_time": 1556084160, 
    "interviewee": "\u8c2d\u9ece\u660e", 
    "phone": "", 
    "birthday": null, 
    "purpose": 0, 
    "come_from": "", 
    "remark": "", 
    "name": "\u79e6\u51e1\u9e4f", 
    "photos": [
      "2019-04-24/v2_23a3de99fbc201c161638c788bcf827a2fc3c139.jpg"
    ], 
    "gender": 0, 
    "end_time": 1581032580, 
    "interviewee_pinyin": "tanliming"
  }, 
  {
    "subject_type": 1, 
    "visit_notify": false, 
    "create_time": 1556105853, 
    "job_number": "0", 
    "title": "", 
    "company_id": 1, 
    "id": 155, 
    "entry_date": null, 
    "department": "", 
    "email": "", 
    "avatar": "2019-04-24/v2_b0846e7082935e26864e34e03707fbd61a4a0c0c.jpg", 
    "password_reseted": false, 
    "description": "", 
    "pinyin": "chentianyu", 
    "start_time": 1556105820, 
    "interviewee": "\u8c2d\u9ece\u660e", 
    "phone": "", 
    "birthday": null, 
    "purpose": 0, 
    "come_from": "", 
    "remark": "", 
    "name": "\u9648\u5929\u5b87", 
    "photos": [
      "2019-04-24/v2_2ad70dd732cc441fae4f25c495616a88f06d807a.jpg"
    ], 
    "gender": 0, 
    "end_time": 1578523080, 
    "interviewee_pinyin": "tanliming"
  }, 
  {
    "subject_type": 1, 
    "visit_notify": false, 
    "create_time": 1556105895, 
    "job_number": "0", 
    "title": "", 
    "company_id": 1, 
    "id": 156, 
    "entry_date": null, 
    "department": "", 
    "email": "", 
    "avatar": "2019-04-24/v2_69a119ccbb2db50ff49ca54b95890e096ce133b4.jpg", 
    "password_reseted": false, 
    "description": "", 
    "pinyin": "yushimo", 
    "start_time": 1555983900, 
    "interviewee": "\u8c2d\u9ece\u660e", 
    "phone": "", 
    "birthday": null, 
    "purpose": 0, 
    "come_from": "", 
    "remark": "", 
    "name": "\u4f59\u4ed5\u58a8", 
    "photos": [
      "2019-04-24/v2_89d99ab2b3679f6db69cf111644fb3c683065682.jpg"
    ], 
    "gender": 0, 
    "end_time": 1576103820, 
    "interviewee_pinyin": "tanliming"
  }, 
  {
    "subject_type": 1, 
    "visit_notify": false, 
    "create_time": 1556105930, 
    "job_number": "0", 
    "title": "", 
    "company_id": 1, 
    "id": 157, 
    "entry_date": null, 
    "department": "", 
    "email": "", 
    "avatar": "2019-04-24/v2_cdb7a62e113770ca2eb74313f1ee131d8d6f0b4d.jpg", 
    "password_reseted": false, 
    "description": "", 
    "pinyin": "liaoguolong", 
    "start_time": 1556073960, 
    "interviewee": "\u8c2d\u9ece\u660e", 
    "phone": "", 
    "birthday": null, 
    "purpose": 0, 
    "come_from": "", 
    "remark": "", 
    "name": "\u5ed6\u56fd\u9f99", 
    "photos": [
      "2019-04-24/v2_9880eaee35f0b9b69c0f75aef6524db6eddb2e1e.jpg"
    ], 
    "gender": 0, 
    "end_time": 1577918280, 
    "interviewee_pinyin": "tanliming"
  }, 
  {
    "subject_type": 1, 
    "visit_notify": false, 
    "create_time": 1556105988, 
    "job_number": "0", 
    "title": "", 
    "company_id": 1, 
    "id": 158, 
    "entry_date": null, 
    "department": "", 
    "email": "", 
    "avatar": "2019-04-24/v2_c3182e2fb2d12aa65b4233d171f2cdaa73bce889.jpg", 
    "password_reseted": false, 
    "description": "", 
    "pinyin": "pengqingsong", 
    "start_time": 1556069940, 
    "interviewee": "\u8c2d\u9ece\u660e", 
    "phone": "", 
    "birthday": null, 
    "purpose": 0, 
    "come_from": "", 
    "remark": "", 
    "name": "\u5f6d\u9752\u677e", 
    "photos": [
      "2019-04-24/v2_d2d1f703bf416f4ff353fc455e51728c58b3cf24.jpg"
    ], 
    "gender": 0, 
    "end_time": 1575632340, 
    "interviewee_pinyin": "tanliming"
  }, 
  {
    "subject_type": 1, 
    "visit_notify": false, 
    "create_time": 1557029284, 
    "job_number": "0", 
    "title": "", 
    "company_id": 1, 
    "id": 162, 
    "entry_date": null, 
    "department": "", 
    "email": "", 
    "avatar": "2019-05-05/v2_0cd212e48033a90e66696e7580f3376be7096b70.jpg", 
    "password_reseted": false, 
    "description": "", 
    "pinyin": "huangtianhua", 
    "start_time": 1556923080, 
    "interviewee": "\u8c2d\u9ece\u660e", 
    "phone": "", 
    "birthday": null, 
    "purpose": 0, 
    "come_from": "\u70e8\u4e91", 
    "remark": "", 
    "name": "\u9ec4\u5929\u534e", 
    "photos": [
      "2019-05-05/v2_88cb3e4d58d40974b8a102ca9967b7e1f60f43a0.jpg"
    ], 
    "gender": 0, 
    "end_time": 1628059740, 
    "interviewee_pinyin": ""
  }, 
  {
    "subject_type": 1, 
    "visit_notify": false, 
    "create_time": 1558924168, 
    "job_number": "0", 
    "title": "", 
    "company_id": 1, 
    "id": 173, 
    "entry_date": null, 
    "department": "", 
    "email": "", 
    "avatar": "2019-05-27/v2_02527ebbe28a25709f4595baa24ccef64d2d81d2.jpg", 
    "password_reseted": false, 
    "description": "", 
    "pinyin": "hejiang", 
    "start_time": 1558886400, 
    "interviewee": "", 
    "phone": "", 
    "birthday": null, 
    "purpose": 0, 
    "come_from": "", 
    "remark": "", 
    "name": "\u4f55\u6c5f", 
    "photos": [
      "2019-05-27/v2_4ad52f535c8d2990104167dcb38f598068e6b4e8.jpg"
    ], 
    "gender": 0, 
    "end_time": 1590854400, 
    "interviewee_pinyin": ""
  }, 
  {
    "subject_type": 1, 
    "visit_notify": false, 
    "create_time": 1558924320, 
    "job_number": "0", 
    "title": "", 
    "company_id": 1, 
    "id": 174, 
    "entry_date": null, 
    "department": "", 
    "email": "", 
    "avatar": "2019-05-27/v2_0748ed4826b0bf070f7feb13bc49ad782f1a5566.jpg", 
    "password_reseted": false, 
    "description": "", 
    "pinyin": "songmingsong", 
    "start_time": 1558886400, 
    "interviewee": "", 
    "phone": "", 
    "birthday": null, 
    "purpose": 0, 
    "come_from": "", 
    "remark": "", 
    "name": "\u5b8b\u660e\u677e", 
    "photos": [
      "2019-05-27/v2_012a5feb11540ecf89d34ed8951ac5389cec2588.jpg"
    ], 
    "gender": 0, 
    "end_time": 1590854400, 
    "interviewee_pinyin": ""
  }, 
  {
    "subject_type": 1, 
    "visit_notify": false, 
    "create_time": 1558924400, 
    "job_number": "0", 
    "title": "", 
    "company_id": 1, 
    "id": 175, 
    "entry_date": null, 
    "department": "", 
    "email": "", 
    "avatar": "2019-05-27/v2_7c6d4a1a6f20db9a3744303e11ecb6852e2fe73e.jpg", 
    "password_reseted": false, 
    "description": "", 
    "pinyin": "zhongyang", 
    "start_time": 1558886400, 
    "interviewee": "", 
    "phone": "", 
    "birthday": null, 
    "purpose": 0, 
    "come_from": "", 
    "remark": "", 
    "name": "\u949f\u626c", 
    "photos": [
      "2019-05-27/v2_576c8572b1d4b3eb4a118abcabe5ee3a010ddf92.jpg"
    ], 
    "gender": 0, 
    "end_time": 1590854400, 
    "interviewee_pinyin": ""
  }, 
  {
    "subject_type": 1, 
    "visit_notify": false, 
    "create_time": 1558924449, 
    "job_number": "0", 
    "title": "", 
    "company_id": 1, 
    "id": 176, 
    "entry_date": null, 
    "department": "", 
    "email": "", 
    "avatar": "2019-05-27/v2_b7e7a343acb746994d7a434bf3e2e3a5abd0f5f2.jpg", 
    "password_reseted": false, 
    "description": "", 
    "pinyin": "zhangchunlin", 
    "start_time": 1558886400, 
    "interviewee": "", 
    "phone": "", 
    "birthday": null, 
    "purpose": 0, 
    "come_from": "", 
    "remark": "", 
    "name": "\u5f20\u6625\u6797", 
    "photos": [
      "2019-05-27/v2_adc831ae3c2f87d108583f684c83b07231fc5776.jpg"
    ], 
    "gender": 0, 
    "end_time": 1590854400, 
    "interviewee_pinyin": ""
  }, 
  {
    "subject_type": 1, 
    "visit_notify": false, 
    "create_time": 1558924496, 
    "job_number": "0", 
    "title": "", 
    "company_id": 1, 
    "id": 177, 
    "entry_date": null, 
    "department": "", 
    "email": "", 
    "avatar": "2019-05-27/v2_2c5fef7827f34346adaf29dbee69eaa2b53b69f5.jpg", 
    "password_reseted": false, 
    "description": "", 
    "pinyin": "luohao", 
    "start_time": 1558886400, 
    "interviewee": "", 
    "phone": "", 
    "birthday": null, 
    "purpose": 0, 
    "come_from": "", 
    "remark": "", 
    "name": "\u7f57\u7693", 
    "photos": [
      "2019-05-27/v2_cbbbb02d52ca82a398df959dd223a9c76f35f977.jpg"
    ], 
    "gender": 0, 
    "end_time": 1590854400, 
    "interviewee_pinyin": ""
  }, 
  {
    "subject_type": 1, 
    "visit_notify": false, 
    "create_time": 1558924561, 
    "job_number": "0", 
    "title": "", 
    "company_id": 1, 
    "id": 178, 
    "entry_date": null, 
    "department": "", 
    "email": "", 
    "avatar": "2019-05-27/v2_c958669739cc9a6103cd05296e790f75d7343e18.jpg", 
    "password_reseted": false, 
    "description": "", 
    "pinyin": "xuwubin", 
    "start_time": 1558886400, 
    "interviewee": "", 
    "phone": "", 
    "birthday": null, 
    "purpose": 0, 
    "come_from": "", 
    "remark": "", 
    "name": "\u8bb8\u5434\u658c", 
    "photos": [
      "2019-05-27/v2_fc6394aebd71bdf8a285de1d505441450859d9d9.jpg"
    ], 
    "gender": 0, 
    "end_time": 1590854400, 
    "interviewee_pinyin": ""
  }, 
  {
    "subject_type": 1, 
    "visit_notify": false, 
    "create_time": 1559210783, 
    "job_number": "0", 
    "title": "", 
    "company_id": 1, 
    "id": 182, 
    "entry_date": null, 
    "department": "", 
    "email": "", 
    "avatar": "2019-05-30/v2_58f68cd7d2638367aacddb5e8c67d66302862664.jpg", 
    "password_reseted": false, 
    "description": "", 
    "pinyin": "jiangwei", 
    "start_time": 1559145600, 
    "interviewee": "", 
    "phone": "", 
    "birthday": null, 
    "purpose": 0, 
    "come_from": "", 
    "remark": "", 
    "name": "\u59dc\u5dcd", 
    "photos": [
      "2019-05-30/v2_c8e9823f97cc83b990965e78979e59e72d31b9ac.jpg"
    ], 
    "gender": 0, 
    "end_time": 1590768000, 
    "interviewee_pinyin": ""
  }, 
  {
    "subject_type": 1, 
    "visit_notify": false, 
    "create_time": 1560160856, 
    "job_number": "0", 
    "title": "", 
    "company_id": 1, 
    "id": 189, 
    "entry_date": null, 
    "department": "", 
    "email": "", 
    "avatar": "2019-06-10/v2_7119ba79e48116c388b69ce9ea314a4e467b71a5.jpg", 
    "password_reseted": false, 
    "description": "", 
    "pinyin": "duzhenyang", 
    "start_time": 1560096000, 
    "interviewee": "", 
    "phone": "", 
    "birthday": null, 
    "purpose": 0, 
    "come_from": "", 
    "remark": "", 
    "name": "\u675c\u632f\u6d0b", 
    "photos": [
      "2019-06-10/v2_cea182d03c795a89e9124545355eba1ff0a693a0.jpg"
    ], 
    "gender": 0, 
    "end_time": 1591718400, 
    "interviewee_pinyin": ""
  }, 
  {
    "subject_type": 1, 
    "visit_notify": false, 
    "create_time": 1560160896, 
    "job_number": "0", 
    "title": "", 
    "company_id": 1, 
    "id": 190, 
    "entry_date": null, 
    "department": "", 
    "email": "", 
    "avatar": "2019-06-10/v2_0f73d9630e286ca9699cbf1b02affedaf639b5c8.jpg", 
    "password_reseted": false, 
    "description": "", 
    "pinyin": "luhandong", 
    "start_time": 1560096000, 
    "interviewee": "", 
    "phone": "", 
    "birthday": null, 
    "purpose": 0, 
    "come_from": "", 
    "remark": "", 
    "name": "\u5362\u5bd2\u51ac", 
    "photos": [
      "2019-06-10/v2_c40ce0582cb7602f572c54ceb000fb74c3cd6ade.jpg"
    ], 
    "gender": 0, 
    "end_time": 1591718400, 
    "interviewee_pinyin": ""
  }
]